pyEncripto/__init__.py
pyEncripto/cli.py
pyEncripto/encryptor.py
pyEncripto/secure_runtime.py
pyencripto-1.0.0.dist-info/METADATA
pyencripto-1.0.0.dist-info/WHEEL
pyencripto-1.0.0.dist-info/entry_points.txt
pyencripto-1.0.0.dist-info/licenses/LICENSE
pyencripto-1.0.0.dist-info/RECORD
