Metadata-Version: 2.4
Name: pyEncripto
Version: 1.0.0
Summary: pyEncripto — a tool for encrypting Python projects and securely running them with encrypted modules and assets
Project-URL: Homepage, https://github.com/andrei1112111/pyEncripto
Project-URL: Issues, https://github.com/andrei1112111/pyEncripto/issues
Author-email: Tishkin Andrei <atishkin060705@gmail.com>
License-File: LICENSE
Classifier: License :: OSI Approved :: MIT License
Classifier: Operating System :: OS Independent
Classifier: Programming Language :: Python :: 3
Requires-Python: >=3.10.0
Requires-Dist: pycryptodome>=3.23.0
